.gitignore
CHANGELOG.md
CONTRIBUTING.md
LICENSE
Makefile
README.md
install.sh
pyproject.toml
setup.cfg
setup.py
.buildkite/pipeline.yml
.buildkite/scripts/benchmark.sh
.buildkite/scripts/benchmark_master.sh
.buildkite/scripts/benchmark_worker.sh
.buildkite/scripts/example.sh
.github/dependabot.yml
.github/issue-close-app.yml
.github/ISSUE_TEMPLATE/bug_report.md
.github/ISSUE_TEMPLATE/feature_request.md
.github/workflows/black.yml
.github/workflows/dockerhub.yml
.github/workflows/flake8.yml
.github/workflows/pypi-publish.yml
.github/workflows/python-package-check.yml
.github/workflows/pytype.yml
.test_to_migrate/test_communication.py
.test_to_migrate/test_flatten.py
.test_to_migrate/test_fused_optimizer.py
.test_to_migrate/nccl/__init__.py
.test_to_migrate/nccl/test_gather.py
.test_to_migrate/nccl/test_p2p.py
.test_to_migrate/qsgd/test_norm_qsgd.py
.test_to_migrate/qsgd/test_qsgd.py
.test_to_migrate/qsgd/utils.py
.test_to_migrate/tools/test_loadbalance.py
bagua/__init__.py
bagua/bagua_define.py
bagua/version.py
bagua.egg-info/PKG-INFO
bagua.egg-info/SOURCES.txt
bagua.egg-info/dependency_links.txt
bagua.egg-info/entry_points.txt
bagua.egg-info/requires.txt
bagua.egg-info/top_level.txt
bagua/distributed/__init__.py
bagua/distributed/launch.py
bagua/distributed/run.py
bagua/script/__init__.py
bagua/script/bagua_sys_perf
bagua/script/baguarun.py
bagua/service/__init__.py
bagua/service/autotune_service.py
bagua/service/autotune_system.py
bagua/service/autotune_task_manager.py
bagua/service/bayesian_optimizer.py
bagua/torch_api/__init__.py
bagua/torch_api/bucket.py
bagua/torch_api/communication.py
bagua/torch_api/distributed.py
bagua/torch_api/env.py
bagua/torch_api/tensor.py
bagua/torch_api/utils.py
bagua/torch_api/algorithms/__init__.py
bagua/torch_api/algorithms/base.py
bagua/torch_api/algorithms/bytegrad.py
bagua/torch_api/algorithms/decentralized.py
bagua/torch_api/algorithms/gradient_allreduce.py
bagua/torch_api/algorithms/q_adam.py
bagua/torch_api/contrib/__init__.py
bagua/torch_api/contrib/fused_optimizer.py
bagua/torch_api/contrib/load_balancing_data_loader.py
docker/Dockerfile.pytorch-1.9.0-cuda10.2-cudnn7
