Metadata-Version: 2.1
Name: bagua
Version: 0.7.0
Summary: Bagua is a flexible and performant distributed training algorithm development framework.
Home-page: https://github.com/BaguaSys/bagua
Author: Kuaishou AI Platform & DS3 Lab
Author-email: admin@mail.xrlian.com
License: UNKNOWN
Platform: UNKNOWN
Requires-Python: >=3.7
License-File: LICENSE
